term/__init__.py
term/adapter.py
term/explainer.py
term/rule.py
term/tree.py
term_rules-0.1.0.dist-info/METADATA
term_rules-0.1.0.dist-info/WHEEL
term_rules-0.1.0.dist-info/licenses/LICENSE
term_rules-0.1.0.dist-info/RECORD
