Metadata-Version: 2.4
Name: term-rules
Version: 0.1.0
Summary: Transparent Easy Rule Model (credit scoring rules)
Project-URL: Homepage, https://github.com/yourname/term-rules
Project-URL: Issues, https://github.com/yourname/term-rules/issues
Author-email: Your Name <you@example.com>
License: MIT License
License-File: LICENSE
Classifier: License :: OSI Approved :: MIT License
Classifier: Operating System :: OS Independent
Classifier: Programming Language :: Python :: 3
Requires-Python: >=3.9
Requires-Dist: bitarray>=2.5.1
Requires-Dist: catboost>=1.2
Requires-Dist: eventlet>=0.33.3
Requires-Dist: gmpy2>=2.1.2
Requires-Dist: lightgbm>=4.0
Requires-Dist: mpmath>=1.3.0
Requires-Dist: numpy>=1.22.3
Requires-Dist: pandas>=1.5.3
Requires-Dist: plotly>=5.0
Requires-Dist: scikit-learn>=1.2.2
Requires-Dist: scipy>=1.8.0
Requires-Dist: tqdm>=4.65.0
Requires-Dist: xgboost>=1.7.6
